{
  "_doc": "ANIMA controlled vocabulary for typed entities & faceted relations. Single source of truth read by extract_triples.py (Phase 1 local extraction), the Wikidata enricher (Phase 2), and the index builder (Phase 3). Buckets are coarse on purpose; precise roles come from Wikidata P106 later. See docs/anima-knowledge-graph.md.",
  "version": 1,
  "kinds": ["person", "place", "organization", "work", "event", "species", "concept"],
  "gender": {
    "M": { "it": "uomo", "en": "man" },
    "F": { "it": "donna", "en": "woman" }
  },
  "occupations": [
    { "bucket": "musician", "it": "musicista", "en": "musician",
      "forms_it": ["musicista", "cantautore", "cantautrice", "cantante", "chitarrista", "compositore", "compositrice", "pianista", "violinista", "polistrumentista", "rapper", "bassista", "batterista", "direttore d'orchestra"],
      "forms_en": ["musician", "singer", "songwriter", "guitarist", "composer", "pianist", "violinist", "rapper", "bassist", "drummer", "vocalist"] },
    { "bucket": "actor", "it": "attore", "en": "actor",
      "forms_it": ["attore", "attrice", "regista", "sceneggiatore", "doppiatore", "comico", "comica"],
      "forms_en": ["actor", "actress", "filmmaker", "screenwriter", "comedian", "voice actor"] },
    { "bucket": "scientist", "it": "scienziato", "en": "scientist",
      "forms_it": ["scienziato", "scienziata", "fisico", "chimico", "matematico", "matematica", "biologo", "astronomo", "naturalista", "inventore", "ingegnere", "geologo", "informatico", "medico"],
      "forms_en": ["scientist", "physicist", "chemist", "mathematician", "biologist", "astronomer", "naturalist", "inventor", "engineer", "geologist", "computer scientist", "physician"] },
    { "bucket": "writer", "it": "scrittore", "en": "writer",
      "forms_it": ["scrittore", "scrittrice", "poeta", "poetessa", "romanziere", "drammaturgo", "saggista", "filosofo", "filosofa", "giornalista", "storico"],
      "forms_en": ["writer", "author", "poet", "novelist", "playwright", "essayist", "philosopher", "journalist", "historian"] },
    { "bucket": "politician", "it": "politico", "en": "politician",
      "forms_it": ["politico", "presidente", "primo ministro", "statista", "rivoluzionario", "attivista", "diplomatico", "senatore", "deputato", "cancelliere"],
      "forms_en": ["politician", "president", "prime minister", "statesman", "revolutionary", "activist", "diplomat", "senator", "chancellor"] },
    { "bucket": "ruler", "it": "sovrano", "en": "ruler",
      "forms_it": ["imperatore", "imperatrice", "regina", "sovrano", "faraone", "zar", "sultano", "condottiero", "generale", "dittatore", "monarca"],
      "forms_en": ["emperor", "empress", "king", "queen", "pharaoh", "tsar", "sultan", "general", "dictator", "monarch", "warlord"] },
    { "bucket": "artist", "it": "artista", "en": "artist",
      "forms_it": ["pittore", "pittrice", "scultore", "scultrice", "architetto", "artista", "fotografo", "disegnatore", "fumettista"],
      "forms_en": ["painter", "sculptor", "architect", "artist", "photographer", "illustrator", "cartoonist"] },
    { "bucket": "athlete", "it": "atleta", "en": "athlete",
      "forms_it": ["calciatore", "calciatrice", "cestista", "pilota", "tennista", "atleta", "ciclista", "pugile", "nuotatore", "sciatore", "schermidore"],
      "forms_en": ["footballer", "basketball player", "racing driver", "tennis player", "athlete", "cyclist", "boxer", "swimmer", "skier"] },
    { "bucket": "religious", "it": "religioso", "en": "religious figure",
      "forms_it": ["papa", "santo", "santa", "vescovo", "cardinale", "teologo", "profeta", "monaco", "missionario"],
      "forms_en": ["pope", "saint", "bishop", "cardinal", "theologian", "prophet", "monk", "missionary"] },
    { "bucket": "business", "it": "imprenditore", "en": "businessperson",
      "forms_it": ["imprenditore", "imprenditrice", "industriale", "banchiere", "magnate"],
      "forms_en": ["businessman", "businesswoman", "entrepreneur", "industrialist", "investor", "magnate"] },
    { "bucket": "explorer", "it": "esploratore", "en": "explorer",
      "forms_it": ["esploratore", "navigatore", "astronauta", "cosmonauta"],
      "forms_en": ["explorer", "navigator", "astronaut", "cosmonaut"] }
  ]
}
